{
  "layer_id": 82,
  "layer_name": "WI Listened to Apple Music Audio Svc 30",
  "description": "Business Analyst Layer: WI Listened to Apple Music Audio Svc 30",
  "geometry_type": "esriGeometryPolygon",
  "extraction_timestamp": "2025-09-21T21:31:43.277524",
  "record_count": 4064,
  "field_count": 14,
  "fields": [
    {
      "name": "OBJECTID",
      "type": "esriFieldTypeOID",
      "alias": "Object ID",
      "nullable": false,
      "domain": null,
      "sample_values": [
        1,
        2,
        3
      ],
      "has_data": true
    },
    {
      "name": "admin4_name",
      "type": "esriFieldTypeString",
      "alias": "ZIP Code",
      "nullable": true,
      "domain": null,
      "sample_values": [
        "54302 (Green Bay)",
        "54313 (Green Bay)",
        "54303 (Green Bay)"
      ],
      "has_data": true
    },
    {
      "name": "admin3_name",
      "type": "esriFieldTypeString",
      "alias": "County",
      "nullable": true,
      "domain": null,
      "sample_values": [
        "Brown County",
        "Brown County",
        "Brown County"
      ],
      "has_data": true
    },
    {
      "name": "admin2_name",
      "type": "esriFieldTypeString",
      "alias": "State",
      "nullable": true,
      "domain": null,
      "sample_values": [
        "Wisconsin",
        "Wisconsin",
        "Wisconsin"
      ],
      "has_data": true
    },
    {
      "name": "id",
      "type": "esriFieldTypeString",
      "alias": "Cell ID",
      "nullable": true,
      "domain": null,
      "sample_values": [
        "86274350fffffff",
        "862743517ffffff",
        "86274351fffffff"
      ],
      "has_data": true
    },
    {
      "name": "MP22088A_B",
      "type": "esriFieldTypeDouble",
      "alias": "2025 Listened to Apple Music Audio Service Last 30 Days",
      "nullable": true,
      "domain": null,
      "sample_values": [
        4580,
        2079,
        5252
      ],
      "has_data": true
    },
    {
      "name": "MP22088A_B_P",
      "type": "esriFieldTypeDouble",
      "alias": "2025 Listened to Apple Music Audio Service Last 30 Days (%)",
      "nullable": true,
      "domain": null,
      "sample_values": [
        16.3,
        15.7,
        15.65
      ],
      "has_data": true
    },
    {
      "name": "thematic_value",
      "type": "esriFieldTypeDouble",
      "alias": "thematic_value",
      "nullable": true,
      "domain": null,
      "sample_values": [
        16.3,
        15.7,
        15.65
      ],
      "has_data": true
    },
    {
      "name": "Shape__Area",
      "type": "esriFieldTypeDouble",
      "alias": "Shape__Area",
      "nullable": true,
      "domain": null,
      "sample_values": [
        75107499.99609375,
        75216250,
        74615000
      ],
      "has_data": true
    },
    {
      "name": "Shape__Length",
      "type": "esriFieldTypeDouble",
      "alias": "Shape__Length",
      "nullable": true,
      "domain": null,
      "sample_values": [
        32271.926106431136,
        32296.975889975613,
        32167.04867856982
      ],
      "has_data": true
    },
    {
      "name": "CreationDate",
      "type": "esriFieldTypeDate",
      "alias": "CreationDate",
      "nullable": true,
      "domain": null,
      "sample_values": [
        1758492880999,
        1758492880999,
        1758492880999
      ],
      "has_data": true
    },
    {
      "name": "Creator",
      "type": "esriFieldTypeString",
      "alias": "Creator",
      "nullable": true,
      "domain": null,
      "sample_values": [
        "Synapse54",
        "Synapse54",
        "Synapse54"
      ],
      "has_data": true
    },
    {
      "name": "EditDate",
      "type": "esriFieldTypeDate",
      "alias": "EditDate",
      "nullable": true,
      "domain": null,
      "sample_values": [
        1758492880999,
        1758492880999,
        1758492880999
      ],
      "has_data": true
    },
    {
      "name": "Editor",
      "type": "esriFieldTypeString",
      "alias": "Editor",
      "nullable": true,
      "domain": null,
      "sample_values": [
        "Synapse54",
        "Synapse54",
        "Synapse54"
      ],
      "has_data": true
    }
  ],
  "csv_file": "layer_82_WI_Listened_to_Apple_Music_Audio_Svc_30.csv"
}