{
  "generated_timestamp": "2025-08-24T17:10:52.910Z",
  "total_fields": 210,
  "files_processed": 24,
  "total_records": 23616,
  "field_categories": {
    "system": [
      "CreationDate",
      "Creator",
      "DESCRIPTION",
      "EditDate",
      "Editor",
      "ID",
      "OBJECTID",
      "Shape__Area",
      "Shape__Length",
      "thematic_value"
    ],
    "mp_codes": [
      "MP10002A_B",
      "MP10002A_B_P",
      "MP10020A_B",
      "MP10020A_B_P",
      "MP10028A_B",
      "MP10028A_B_P",
      "MP10104A_B",
      "MP10104A_B_P",
      "MP10110A_B",
      "MP10110A_B_P",
      "MP10116A_B",
      "MP10116A_B_P",
      "MP10120A_B",
      "MP10120A_B_P",
      "MP10128A_B",
      "MP10128A_B_P",
      "MP10138A_B",
      "MP10138A_B_P"
    ],
    "x_codes": [
      "X14058_X",
      "X14058_X_A",
      "X14060_X",
      "X14060_X_A",
      "X14068_X",
      "X14068_X_A"
    ],
    "generation": [
      "GENALPHACY",
      "GENALPHACY_P",
      "GENZ_CY",
      "GENZ_CY_P"
    ],
    "location": [
      "LATITUDE",
      "LONGITUDE",
      "address",
      "country",
      "locality",
      "name",
      "postcode",
      "region"
    ],
    "analysis_scores": [
      "algorithm_agreement_score",
      "algorithm_comparison_score",
      "algorithm_performance_score",
      "algorithm_reliability_score",
      "algorithm_suitability_score",
      "alternative_algorithm_score",
      "analysis_score",
      "analyze_score",
      "anomaly_detection_score",
      "anomaly_insight_score",
      "anomaly_insights_score",
      "anomaly_performance_score",
      "anomaly_reliability_score",
      "anomaly_score",
      "anomaly_significance_score",
      "best_algorithm_confidence_score",
      "brand_difference_score",
      "cluster_analysis_score",
      "cluster_performance_score",
      "cluster_score",
      "comparative_analysis_score",
      "comparative_score",
      "comparison_score",
      "competitive_advantage_score",
      "competitive_analysis_score",
      "competitive_score",
      "component_significance_score",
      "consensus_analysis_score",
      "consensus_confidence_score",
      "consensus_performance_score",
      "consensus_score",
      "correlation_analysis_score",
      "correlation_score",
      "correlation_strength_score",
      "customer_profile_score",
      "data_complexity_score",
      "demographic_insights_score",
      "demographic_opportunity_score",
      "demographic_score",
      "dimensionality_insights_score",
      "dimensionality_performance_score",
      "dimensionality_reduction_benefit_score",
      "dimensionality_score",
      "ensemble_analysis_score",
      "ensemble_confidence_score",
      "ensemble_opportunity_score",
      "ensemble_performance_score",
      "ensemble_reliability_score",
      "ensemble_strength_score",
      "feature_compression_score",
      "feature_importance_clarity_score",
      "feature_importance_ranking_score",
      "feature_importance_score",
      "feature_interaction_score",
      "feature_interactions_score",
      "feature_relationship_strength_score",
      "importance_score",
      "interaction_score",
      "interpretability_benefit_score",
      "investigation_priority_score",
      "market_anomaly_value_score",
      "model_agreement_score",
      "model_component_strength_score",
      "model_diversity_benefit_score",
      "model_performance_prediction_score",
      "model_performance_score",
      "model_selection_performance_score",
      "model_selection_score",
      "multi_model_value_score",
      "opportunity_detection_score",
      "opportunity_score",
      "outlier_detection_score",
      "outlier_score",
      "outlier_strength_score",
      "performance_score",
      "prediction_consensus_score",
      "prediction_precision_score",
      "prediction_reliability_score",
      "predictive_modeling_score",
      "predictive_score",
      "recommendation_confidence_score",
      "scenario_analysis_score",
      "scenario_score",
      "segment_profiling_score",
      "segment_score",
      "selection_reliability_score",
      "sensitivity_analysis_score",
      "sensitivity_score",
      "spatial_clusters_score",
      "strategic_analysis_score",
      "strategic_score",
      "strategic_value_score",
      "trend_analysis_score",
      "trend_score",
      "trend_strength_score",
      "uncertainty_quantification_score",
      "voting_consensus_strength_score"
    ],
    "other": [
      "DESC_",
      "INDUSTRY_DESC",
      "algorithm_agreement",
      "algorithm_category",
      "algorithm_predictions",
      "alternative_algorithms",
      "anomaly_category",
      "anomaly_explanation",
      "anomaly_type",
      "best_algorithm",
      "clear_feature_hierarchy",
      "cluster_id",
      "cluster_label",
      "competitive_components",
      "competitive_position",
      "component_contributions",
      "component_weights",
      "consensus_prediction",
      "consensus_quality",
      "data_complexity_category",
      "data_reliability",
      "demographic_advantage",
      "economic_advantage",
      "ensemble_included",
      "ensemble_prediction",
      "esri_pid",
      "exceptional_confidence",
      "feature_loadings",
      "fsq_category",
      "fsq_category_all",
      "high_compression_efficiency",
      "high_confidence_recommendation",
      "high_model_agreement",
      "high_opportunity_anomaly",
      "high_performance_expected",
      "high_performance_prediction",
      "interpretable_choice",
      "investigation_recommended",
      "is_anomaly",
      "low_uncertainty",
      "market_dominance",
      "market_opportunity",
      "market_scale",
      "model_contributions",
      "model_predictions",
      "opportunity_rating",
      "optimal_algorithm_match",
      "performance_metrics",
      "pointCount",
      "population_advantage",
      "positive_market_signal",
      "prediction_confidence",
      "prediction_interval",
      "primary_component_interpretation",
      "recommendation_confidence",
      "recommended_algorithm",
      "reliable_consensus",
      "selection_reasoning",
      "significant_dimensionality_reduction",
      "source",
      "strong_feature_relationships",
      "strong_outlier",
      "strong_voting_consensus",
      "uncertainty_measures",
      "value",
      "variance_explained",
      "voting_results"
    ]
  },
  "all_fields_sorted": [
    "CreationDate",
    "Creator",
    "DESCRIPTION",
    "DESC_",
    "EditDate",
    "Editor",
    "GENALPHACY",
    "GENALPHACY_P",
    "GENZ_CY",
    "GENZ_CY_P",
    "ID",
    "INDUSTRY_DESC",
    "LATITUDE",
    "LONGITUDE",
    "MP10002A_B",
    "MP10002A_B_P",
    "MP10020A_B",
    "MP10020A_B_P",
    "MP10028A_B",
    "MP10028A_B_P",
    "MP10104A_B",
    "MP10104A_B_P",
    "MP10110A_B",
    "MP10110A_B_P",
    "MP10116A_B",
    "MP10116A_B_P",
    "MP10120A_B",
    "MP10120A_B_P",
    "MP10128A_B",
    "MP10128A_B_P",
    "MP10138A_B",
    "MP10138A_B_P",
    "OBJECTID",
    "Shape__Area",
    "Shape__Length",
    "X14058_X",
    "X14058_X_A",
    "X14060_X",
    "X14060_X_A",
    "X14068_X",
    "X14068_X_A",
    "address",
    "algorithm_agreement",
    "algorithm_agreement_score",
    "algorithm_category",
    "algorithm_comparison_score",
    "algorithm_performance_score",
    "algorithm_predictions",
    "algorithm_reliability_score",
    "algorithm_suitability_score",
    "alternative_algorithm_score",
    "alternative_algorithms",
    "analysis_score",
    "analyze_score",
    "anomaly_category",
    "anomaly_detection_score",
    "anomaly_explanation",
    "anomaly_insight_score",
    "anomaly_insights_score",
    "anomaly_performance_score",
    "anomaly_reliability_score",
    "anomaly_score",
    "anomaly_significance_score",
    "anomaly_type",
    "best_algorithm",
    "best_algorithm_confidence_score",
    "brand_difference_score",
    "clear_feature_hierarchy",
    "cluster_analysis_score",
    "cluster_id",
    "cluster_label",
    "cluster_performance_score",
    "cluster_score",
    "comparative_analysis_score",
    "comparative_score",
    "comparison_score",
    "competitive_advantage_score",
    "competitive_analysis_score",
    "competitive_components",
    "competitive_position",
    "competitive_score",
    "component_contributions",
    "component_significance_score",
    "component_weights",
    "consensus_analysis_score",
    "consensus_confidence_score",
    "consensus_performance_score",
    "consensus_prediction",
    "consensus_quality",
    "consensus_score",
    "correlation_analysis_score",
    "correlation_score",
    "correlation_strength_score",
    "country",
    "customer_profile_score",
    "data_complexity_category",
    "data_complexity_score",
    "data_reliability",
    "demographic_advantage",
    "demographic_insights_score",
    "demographic_opportunity_score",
    "demographic_score",
    "dimensionality_insights_score",
    "dimensionality_performance_score",
    "dimensionality_reduction_benefit_score",
    "dimensionality_score",
    "economic_advantage",
    "ensemble_analysis_score",
    "ensemble_confidence_score",
    "ensemble_included",
    "ensemble_opportunity_score",
    "ensemble_performance_score",
    "ensemble_prediction",
    "ensemble_reliability_score",
    "ensemble_strength_score",
    "esri_pid",
    "exceptional_confidence",
    "feature_compression_score",
    "feature_importance_clarity_score",
    "feature_importance_ranking_score",
    "feature_importance_score",
    "feature_interaction_score",
    "feature_interactions_score",
    "feature_loadings",
    "feature_relationship_strength_score",
    "fsq_category",
    "fsq_category_all",
    "high_compression_efficiency",
    "high_confidence_recommendation",
    "high_model_agreement",
    "high_opportunity_anomaly",
    "high_performance_expected",
    "high_performance_prediction",
    "importance_score",
    "interaction_score",
    "interpretability_benefit_score",
    "interpretable_choice",
    "investigation_priority_score",
    "investigation_recommended",
    "is_anomaly",
    "locality",
    "low_uncertainty",
    "market_anomaly_value_score",
    "market_dominance",
    "market_opportunity",
    "market_scale",
    "model_agreement_score",
    "model_component_strength_score",
    "model_contributions",
    "model_diversity_benefit_score",
    "model_performance_prediction_score",
    "model_performance_score",
    "model_predictions",
    "model_selection_performance_score",
    "model_selection_score",
    "multi_model_value_score",
    "name",
    "opportunity_detection_score",
    "opportunity_rating",
    "opportunity_score",
    "optimal_algorithm_match",
    "outlier_detection_score",
    "outlier_score",
    "outlier_strength_score",
    "performance_metrics",
    "performance_score",
    "pointCount",
    "population_advantage",
    "positive_market_signal",
    "postcode",
    "prediction_confidence",
    "prediction_consensus_score",
    "prediction_interval",
    "prediction_precision_score",
    "prediction_reliability_score",
    "predictive_modeling_score",
    "predictive_score",
    "primary_component_interpretation",
    "recommendation_confidence",
    "recommendation_confidence_score",
    "recommended_algorithm",
    "region",
    "reliable_consensus",
    "scenario_analysis_score",
    "scenario_score",
    "segment_profiling_score",
    "segment_score",
    "selection_reasoning",
    "selection_reliability_score",
    "sensitivity_analysis_score",
    "sensitivity_score",
    "significant_dimensionality_reduction",
    "source",
    "spatial_clusters_score",
    "strategic_analysis_score",
    "strategic_score",
    "strategic_value_score",
    "strong_feature_relationships",
    "strong_outlier",
    "strong_voting_consensus",
    "thematic_value",
    "trend_analysis_score",
    "trend_score",
    "trend_strength_score",
    "uncertainty_measures",
    "uncertainty_quantification_score",
    "value",
    "variance_explained",
    "voting_consensus_strength_score",
    "voting_results"
  ],
  "field_sources": {
    "ID": [
      "algorithm-comparison",
      "analyze",
      "anomaly-detection",
      "anomaly-insights",
      "brand-difference",
      "comparative-analysis",
      "competitive-analysis",
      "consensus-analysis",
      "correlation-analysis",
      "demographic-insights",
      "dimensionality-insights",
      "ensemble-analysis",
      "feature-importance-ranking",
      "feature-interactions",
      "model-performance",
      "model-selection",
      "outlier-detection",
      "predictive-modeling",
      "scenario-analysis",
      "segment-profiling",
      "sensitivity-analysis",
      "spatial-clusters",
      "strategic-analysis",
      "trend-analysis"
    ],
    "DESCRIPTION": [
      "algorithm-comparison",
      "analyze",
      "anomaly-detection",
      "anomaly-insights",
      "brand-difference",
      "comparative-analysis",
      "competitive-analysis",
      "consensus-analysis",
      "correlation-analysis",
      "demographic-insights",
      "dimensionality-insights",
      "ensemble-analysis",
      "feature-importance-ranking",
      "feature-interactions",
      "model-performance",
      "model-selection",
      "outlier-detection",
      "predictive-modeling",
      "scenario-analysis",
      "segment-profiling",
      "sensitivity-analysis",
      "spatial-clusters",
      "strategic-analysis",
      "trend-analysis"
    ],
    "OBJECTID": [
      "algorithm-comparison",
      "analyze",
      "anomaly-detection",
      "anomaly-insights",
      "brand-difference",
      "comparative-analysis",
      "competitive-analysis",
      "consensus-analysis",
      "correlation-analysis",
      "demographic-insights",
      "dimensionality-insights",
      "ensemble-analysis",
      "feature-importance-ranking",
      "feature-interactions",
      "model-performance",
      "model-selection",
      "outlier-detection",
      "predictive-modeling",
      "scenario-analysis",
      "segment-profiling",
      "sensitivity-analysis",
      "spatial-clusters",
      "strategic-analysis",
      "trend-analysis"
    ],
    "MP10104A_B": [
      "algorithm-comparison",
      "analyze",
      "anomaly-detection",
      "anomaly-insights",
      "brand-difference",
      "comparative-analysis",
      "competitive-analysis",
      "consensus-analysis",
      "correlation-analysis",
      "demographic-insights",
      "dimensionality-insights",
      "ensemble-analysis",
      "feature-importance-ranking",
      "feature-interactions",
      "model-performance",
      "model-selection",
      "outlier-detection",
      "predictive-modeling",
      "scenario-analysis",
      "segment-profiling",
      "sensitivity-analysis",
      "spatial-clusters",
      "strategic-analysis",
      "trend-analysis"
    ],
    "MP10104A_B_P": [
      "algorithm-comparison",
      "analyze",
      "anomaly-detection",
      "anomaly-insights",
      "brand-difference",
      "comparative-analysis",
      "competitive-analysis",
      "consensus-analysis",
      "correlation-analysis",
      "demographic-insights",
      "dimensionality-insights",
      "ensemble-analysis",
      "feature-importance-ranking",
      "feature-interactions",
      "model-performance",
      "model-selection",
      "outlier-detection",
      "predictive-modeling",
      "scenario-analysis",
      "segment-profiling",
      "sensitivity-analysis",
      "spatial-clusters",
      "strategic-analysis",
      "trend-analysis"
    ],
    "thematic_value": [
      "algorithm-comparison",
      "analyze",
      "anomaly-detection",
      "anomaly-insights",
      "brand-difference",
      "comparative-analysis",
      "competitive-analysis",
      "consensus-analysis",
      "correlation-analysis",
      "demographic-insights",
      "dimensionality-insights",
      "ensemble-analysis",
      "feature-importance-ranking",
      "feature-interactions",
      "model-performance",
      "model-selection",
      "outlier-detection",
      "predictive-modeling",
      "scenario-analysis",
      "segment-profiling",
      "sensitivity-analysis",
      "spatial-clusters",
      "strategic-analysis",
      "trend-analysis"
    ],
    "Shape__Area": [
      "algorithm-comparison",
      "analyze",
      "anomaly-detection",
      "anomaly-insights",
      "brand-difference",
      "comparative-analysis",
      "competitive-analysis",
      "consensus-analysis",
      "correlation-analysis",
      "demographic-insights",
      "dimensionality-insights",
      "ensemble-analysis",
      "feature-importance-ranking",
      "feature-interactions",
      "model-performance",
      "model-selection",
      "outlier-detection",
      "predictive-modeling",
      "scenario-analysis",
      "segment-profiling",
      "sensitivity-analysis",
      "spatial-clusters",
      "strategic-analysis",
      "trend-analysis"
    ],
    "Shape__Length": [
      "algorithm-comparison",
      "analyze",
      "anomaly-detection",
      "anomaly-insights",
      "brand-difference",
      "comparative-analysis",
      "competitive-analysis",
      "consensus-analysis",
      "correlation-analysis",
      "demographic-insights",
      "dimensionality-insights",
      "ensemble-analysis",
      "feature-importance-ranking",
      "feature-interactions",
      "model-performance",
      "model-selection",
      "outlier-detection",
      "predictive-modeling",
      "scenario-analysis",
      "segment-profiling",
      "sensitivity-analysis",
      "spatial-clusters",
      "strategic-analysis",
      "trend-analysis"
    ],
    "CreationDate": [
      "algorithm-comparison",
      "analyze",
      "anomaly-detection",
      "anomaly-insights",
      "brand-difference",
      "comparative-analysis",
      "competitive-analysis",
      "consensus-analysis",
      "correlation-analysis",
      "demographic-insights",
      "dimensionality-insights",
      "ensemble-analysis",
      "feature-importance-ranking",
      "feature-interactions",
      "model-performance",
      "model-selection",
      "outlier-detection",
      "predictive-modeling",
      "scenario-analysis",
      "segment-profiling",
      "sensitivity-analysis",
      "spatial-clusters",
      "strategic-analysis",
      "trend-analysis"
    ],
    "Creator": [
      "algorithm-comparison",
      "analyze",
      "anomaly-detection",
      "anomaly-insights",
      "brand-difference",
      "comparative-analysis",
      "competitive-analysis",
      "consensus-analysis",
      "correlation-analysis",
      "demographic-insights",
      "dimensionality-insights",
      "ensemble-analysis",
      "feature-importance-ranking",
      "feature-interactions",
      "model-performance",
      "model-selection",
      "outlier-detection",
      "predictive-modeling",
      "scenario-analysis",
      "segment-profiling",
      "sensitivity-analysis",
      "spatial-clusters",
      "strategic-analysis",
      "trend-analysis"
    ],
    "EditDate": [
      "algorithm-comparison",
      "analyze",
      "anomaly-detection",
      "anomaly-insights",
      "brand-difference",
      "comparative-analysis",
      "competitive-analysis",
      "consensus-analysis",
      "correlation-analysis",
      "demographic-insights",
      "dimensionality-insights",
      "ensemble-analysis",
      "feature-importance-ranking",
      "feature-interactions",
      "model-performance",
      "model-selection",
      "outlier-detection",
      "predictive-modeling",
      "scenario-analysis",
      "segment-profiling",
      "sensitivity-analysis",
      "spatial-clusters",
      "strategic-analysis",
      "trend-analysis"
    ],
    "Editor": [
      "algorithm-comparison",
      "analyze",
      "anomaly-detection",
      "anomaly-insights",
      "brand-difference",
      "comparative-analysis",
      "competitive-analysis",
      "consensus-analysis",
      "correlation-analysis",
      "demographic-insights",
      "dimensionality-insights",
      "ensemble-analysis",
      "feature-importance-ranking",
      "feature-interactions",
      "model-performance",
      "model-selection",
      "outlier-detection",
      "predictive-modeling",
      "scenario-analysis",
      "segment-profiling",
      "sensitivity-analysis",
      "spatial-clusters",
      "strategic-analysis",
      "trend-analysis"
    ],
    "X14060_X": [
      "algorithm-comparison",
      "analyze",
      "anomaly-detection",
      "anomaly-insights",
      "brand-difference",
      "comparative-analysis",
      "competitive-analysis",
      "consensus-analysis",
      "correlation-analysis",
      "demographic-insights",
      "dimensionality-insights",
      "ensemble-analysis",
      "feature-importance-ranking",
      "feature-interactions",
      "model-performance",
      "model-selection",
      "outlier-detection",
      "predictive-modeling",
      "scenario-analysis",
      "segment-profiling",
      "sensitivity-analysis",
      "spatial-clusters",
      "strategic-analysis",
      "trend-analysis"
    ],
    "X14060_X_A": [
      "algorithm-comparison",
      "analyze",
      "anomaly-detection",
      "anomaly-insights",
      "brand-difference",
      "comparative-analysis",
      "competitive-analysis",
      "consensus-analysis",
      "correlation-analysis",
      "demographic-insights",
      "dimensionality-insights",
      "ensemble-analysis",
      "feature-importance-ranking",
      "feature-interactions",
      "model-performance",
      "model-selection",
      "outlier-detection",
      "predictive-modeling",
      "scenario-analysis",
      "segment-profiling",
      "sensitivity-analysis",
      "spatial-clusters",
      "strategic-analysis",
      "trend-analysis"
    ],
    "pointCount": [
      "algorithm-comparison",
      "analyze",
      "anomaly-detection",
      "anomaly-insights",
      "brand-difference",
      "comparative-analysis",
      "competitive-analysis",
      "consensus-analysis",
      "correlation-analysis",
      "demographic-insights",
      "dimensionality-insights",
      "ensemble-analysis",
      "feature-importance-ranking",
      "feature-interactions",
      "model-performance",
      "model-selection",
      "outlier-detection",
      "predictive-modeling",
      "scenario-analysis",
      "segment-profiling",
      "sensitivity-analysis",
      "spatial-clusters",
      "strategic-analysis",
      "trend-analysis"
    ],
    "MP10002A_B": [
      "algorithm-comparison",
      "analyze",
      "anomaly-detection",
      "anomaly-insights",
      "brand-difference",
      "comparative-analysis",
      "competitive-analysis",
      "consensus-analysis",
      "correlation-analysis",
      "demographic-insights",
      "dimensionality-insights",
      "ensemble-analysis",
      "feature-importance-ranking",
      "feature-interactions",
      "model-performance",
      "model-selection",
      "outlier-detection",
      "predictive-modeling",
      "scenario-analysis",
      "segment-profiling",
      "sensitivity-analysis",
      "spatial-clusters",
      "strategic-analysis",
      "trend-analysis"
    ],
    "MP10002A_B_P": [
      "algorithm-comparison",
      "analyze",
      "anomaly-detection",
      "anomaly-insights",
      "brand-difference",
      "comparative-analysis",
      "competitive-analysis",
      "consensus-analysis",
      "correlation-analysis",
      "demographic-insights",
      "dimensionality-insights",
      "ensemble-analysis",
      "feature-importance-ranking",
      "feature-interactions",
      "model-performance",
      "model-selection",
      "outlier-detection",
      "predictive-modeling",
      "scenario-analysis",
      "segment-profiling",
      "sensitivity-analysis",
      "spatial-clusters",
      "strategic-analysis",
      "trend-analysis"
    ],
    "X14068_X": [
      "algorithm-comparison",
      "analyze",
      "anomaly-detection",
      "anomaly-insights",
      "brand-difference",
      "comparative-analysis",
      "competitive-analysis",
      "consensus-analysis",
      "correlation-analysis",
      "demographic-insights",
      "dimensionality-insights",
      "ensemble-analysis",
      "feature-importance-ranking",
      "feature-interactions",
      "model-performance",
      "model-selection",
      "outlier-detection",
      "predictive-modeling",
      "scenario-analysis",
      "segment-profiling",
      "sensitivity-analysis",
      "spatial-clusters",
      "strategic-analysis",
      "trend-analysis"
    ],
    "X14068_X_A": [
      "algorithm-comparison",
      "analyze",
      "anomaly-detection",
      "anomaly-insights",
      "brand-difference",
      "comparative-analysis",
      "competitive-analysis",
      "consensus-analysis",
      "correlation-analysis",
      "demographic-insights",
      "dimensionality-insights",
      "ensemble-analysis",
      "feature-importance-ranking",
      "feature-interactions",
      "model-performance",
      "model-selection",
      "outlier-detection",
      "predictive-modeling",
      "scenario-analysis",
      "segment-profiling",
      "sensitivity-analysis",
      "spatial-clusters",
      "strategic-analysis",
      "trend-analysis"
    ],
    "MP10116A_B": [
      "algorithm-comparison",
      "analyze",
      "anomaly-detection",
      "anomaly-insights",
      "brand-difference",
      "comparative-analysis",
      "competitive-analysis",
      "consensus-analysis",
      "correlation-analysis",
      "demographic-insights",
      "dimensionality-insights",
      "ensemble-analysis",
      "feature-importance-ranking",
      "feature-interactions",
      "model-performance",
      "model-selection",
      "outlier-detection",
      "predictive-modeling",
      "scenario-analysis",
      "segment-profiling",
      "sensitivity-analysis",
      "spatial-clusters",
      "strategic-analysis",
      "trend-analysis"
    ],
    "MP10116A_B_P": [
      "algorithm-comparison",
      "analyze",
      "anomaly-detection",
      "anomaly-insights",
      "brand-difference",
      "comparative-analysis",
      "competitive-analysis",
      "consensus-analysis",
      "correlation-analysis",
      "demographic-insights",
      "dimensionality-insights",
      "ensemble-analysis",
      "feature-importance-ranking",
      "feature-interactions",
      "model-performance",
      "model-selection",
      "outlier-detection",
      "predictive-modeling",
      "scenario-analysis",
      "segment-profiling",
      "sensitivity-analysis",
      "spatial-clusters",
      "strategic-analysis",
      "trend-analysis"
    ],
    "name": [
      "algorithm-comparison",
      "analyze",
      "anomaly-detection",
      "anomaly-insights",
      "brand-difference",
      "comparative-analysis",
      "competitive-analysis",
      "consensus-analysis",
      "correlation-analysis",
      "demographic-insights",
      "dimensionality-insights",
      "ensemble-analysis",
      "feature-importance-ranking",
      "feature-interactions",
      "model-performance",
      "model-selection",
      "outlier-detection",
      "predictive-modeling",
      "scenario-analysis",
      "segment-profiling",
      "sensitivity-analysis",
      "spatial-clusters",
      "strategic-analysis",
      "trend-analysis"
    ],
    "address": [
      "algorithm-comparison",
      "analyze",
      "anomaly-detection",
      "anomaly-insights",
      "brand-difference",
      "comparative-analysis",
      "competitive-analysis",
      "consensus-analysis",
      "correlation-analysis",
      "demographic-insights",
      "dimensionality-insights",
      "ensemble-analysis",
      "feature-importance-ranking",
      "feature-interactions",
      "model-performance",
      "model-selection",
      "outlier-detection",
      "predictive-modeling",
      "scenario-analysis",
      "segment-profiling",
      "sensitivity-analysis",
      "spatial-clusters",
      "strategic-analysis",
      "trend-analysis"
    ],
    "locality": [
      "algorithm-comparison",
      "analyze",
      "anomaly-detection",
      "anomaly-insights",
      "brand-difference",
      "comparative-analysis",
      "competitive-analysis",
      "consensus-analysis",
      "correlation-analysis",
      "demographic-insights",
      "dimensionality-insights",
      "ensemble-analysis",
      "feature-importance-ranking",
      "feature-interactions",
      "model-performance",
      "model-selection",
      "outlier-detection",
      "predictive-modeling",
      "scenario-analysis",
      "segment-profiling",
      "sensitivity-analysis",
      "spatial-clusters",
      "strategic-analysis",
      "trend-analysis"
    ],
    "region": [
      "algorithm-comparison",
      "analyze",
      "anomaly-detection",
      "anomaly-insights",
      "brand-difference",
      "comparative-analysis",
      "competitive-analysis",
      "consensus-analysis",
      "correlation-analysis",
      "demographic-insights",
      "dimensionality-insights",
      "ensemble-analysis",
      "feature-importance-ranking",
      "feature-interactions",
      "model-performance",
      "model-selection",
      "outlier-detection",
      "predictive-modeling",
      "scenario-analysis",
      "segment-profiling",
      "sensitivity-analysis",
      "spatial-clusters",
      "strategic-analysis",
      "trend-analysis"
    ],
    "postcode": [
      "algorithm-comparison",
      "analyze",
      "anomaly-detection",
      "anomaly-insights",
      "brand-difference",
      "comparative-analysis",
      "competitive-analysis",
      "consensus-analysis",
      "correlation-analysis",
      "demographic-insights",
      "dimensionality-insights",
      "ensemble-analysis",
      "feature-importance-ranking",
      "feature-interactions",
      "model-performance",
      "model-selection",
      "outlier-detection",
      "predictive-modeling",
      "scenario-analysis",
      "segment-profiling",
      "sensitivity-analysis",
      "spatial-clusters",
      "strategic-analysis",
      "trend-analysis"
    ],
    "country": [
      "algorithm-comparison",
      "analyze",
      "anomaly-detection",
      "anomaly-insights",
      "brand-difference",
      "comparative-analysis",
      "competitive-analysis",
      "consensus-analysis",
      "correlation-analysis",
      "demographic-insights",
      "dimensionality-insights",
      "ensemble-analysis",
      "feature-importance-ranking",
      "feature-interactions",
      "model-performance",
      "model-selection",
      "outlier-detection",
      "predictive-modeling",
      "scenario-analysis",
      "segment-profiling",
      "sensitivity-analysis",
      "spatial-clusters",
      "strategic-analysis",
      "trend-analysis"
    ],
    "fsq_category": [
      "algorithm-comparison",
      "analyze",
      "anomaly-detection",
      "anomaly-insights",
      "brand-difference",
      "comparative-analysis",
      "competitive-analysis",
      "consensus-analysis",
      "correlation-analysis",
      "demographic-insights",
      "dimensionality-insights",
      "ensemble-analysis",
      "feature-importance-ranking",
      "feature-interactions",
      "model-performance",
      "model-selection",
      "outlier-detection",
      "predictive-modeling",
      "scenario-analysis",
      "segment-profiling",
      "sensitivity-analysis",
      "spatial-clusters",
      "strategic-analysis",
      "trend-analysis"
    ],
    "fsq_category_all": [
      "algorithm-comparison",
      "analyze",
      "anomaly-detection",
      "anomaly-insights",
      "brand-difference",
      "comparative-analysis",
      "competitive-analysis",
      "consensus-analysis",
      "correlation-analysis",
      "demographic-insights",
      "dimensionality-insights",
      "ensemble-analysis",
      "feature-importance-ranking",
      "feature-interactions",
      "model-performance",
      "model-selection",
      "outlier-detection",
      "predictive-modeling",
      "scenario-analysis",
      "segment-profiling",
      "sensitivity-analysis",
      "spatial-clusters",
      "strategic-analysis",
      "trend-analysis"
    ],
    "INDUSTRY_DESC": [
      "algorithm-comparison",
      "analyze",
      "anomaly-detection",
      "anomaly-insights",
      "brand-difference",
      "comparative-analysis",
      "competitive-analysis",
      "consensus-analysis",
      "correlation-analysis",
      "demographic-insights",
      "dimensionality-insights",
      "ensemble-analysis",
      "feature-importance-ranking",
      "feature-interactions",
      "model-performance",
      "model-selection",
      "outlier-detection",
      "predictive-modeling",
      "scenario-analysis",
      "segment-profiling",
      "sensitivity-analysis",
      "spatial-clusters",
      "strategic-analysis",
      "trend-analysis"
    ],
    "source": [
      "algorithm-comparison",
      "analyze",
      "anomaly-detection",
      "anomaly-insights",
      "brand-difference",
      "comparative-analysis",
      "competitive-analysis",
      "consensus-analysis",
      "correlation-analysis",
      "demographic-insights",
      "dimensionality-insights",
      "ensemble-analysis",
      "feature-importance-ranking",
      "feature-interactions",
      "model-performance",
      "model-selection",
      "outlier-detection",
      "predictive-modeling",
      "scenario-analysis",
      "segment-profiling",
      "sensitivity-analysis",
      "spatial-clusters",
      "strategic-analysis",
      "trend-analysis"
    ],
    "esri_pid": [
      "algorithm-comparison",
      "analyze",
      "anomaly-detection",
      "anomaly-insights",
      "brand-difference",
      "comparative-analysis",
      "competitive-analysis",
      "consensus-analysis",
      "correlation-analysis",
      "demographic-insights",
      "dimensionality-insights",
      "ensemble-analysis",
      "feature-importance-ranking",
      "feature-interactions",
      "model-performance",
      "model-selection",
      "outlier-detection",
      "predictive-modeling",
      "scenario-analysis",
      "segment-profiling",
      "sensitivity-analysis",
      "spatial-clusters",
      "strategic-analysis",
      "trend-analysis"
    ],
    "DESC_": [
      "algorithm-comparison",
      "analyze",
      "anomaly-detection",
      "anomaly-insights",
      "brand-difference",
      "comparative-analysis",
      "competitive-analysis",
      "consensus-analysis",
      "correlation-analysis",
      "demographic-insights",
      "dimensionality-insights",
      "ensemble-analysis",
      "feature-importance-ranking",
      "feature-interactions",
      "model-performance",
      "model-selection",
      "outlier-detection",
      "predictive-modeling",
      "scenario-analysis",
      "segment-profiling",
      "sensitivity-analysis",
      "spatial-clusters",
      "strategic-analysis",
      "trend-analysis"
    ],
    "LATITUDE": [
      "algorithm-comparison",
      "analyze",
      "anomaly-detection",
      "anomaly-insights",
      "brand-difference",
      "comparative-analysis",
      "competitive-analysis",
      "consensus-analysis",
      "correlation-analysis",
      "demographic-insights",
      "dimensionality-insights",
      "ensemble-analysis",
      "feature-importance-ranking",
      "feature-interactions",
      "model-performance",
      "model-selection",
      "outlier-detection",
      "predictive-modeling",
      "scenario-analysis",
      "segment-profiling",
      "sensitivity-analysis",
      "spatial-clusters",
      "strategic-analysis",
      "trend-analysis"
    ],
    "LONGITUDE": [
      "algorithm-comparison",
      "analyze",
      "anomaly-detection",
      "anomaly-insights",
      "brand-difference",
      "comparative-analysis",
      "competitive-analysis",
      "consensus-analysis",
      "correlation-analysis",
      "demographic-insights",
      "dimensionality-insights",
      "ensemble-analysis",
      "feature-importance-ranking",
      "feature-interactions",
      "model-performance",
      "model-selection",
      "outlier-detection",
      "predictive-modeling",
      "scenario-analysis",
      "segment-profiling",
      "sensitivity-analysis",
      "spatial-clusters",
      "strategic-analysis",
      "trend-analysis"
    ],
    "MP10128A_B": [
      "algorithm-comparison",
      "analyze",
      "anomaly-detection",
      "anomaly-insights",
      "brand-difference",
      "comparative-analysis",
      "competitive-analysis",
      "consensus-analysis",
      "correlation-analysis",
      "demographic-insights",
      "dimensionality-insights",
      "ensemble-analysis",
      "feature-importance-ranking",
      "feature-interactions",
      "model-performance",
      "model-selection",
      "outlier-detection",
      "predictive-modeling",
      "scenario-analysis",
      "segment-profiling",
      "sensitivity-analysis",
      "spatial-clusters",
      "strategic-analysis",
      "trend-analysis"
    ],
    "MP10128A_B_P": [
      "algorithm-comparison",
      "analyze",
      "anomaly-detection",
      "anomaly-insights",
      "brand-difference",
      "comparative-analysis",
      "competitive-analysis",
      "consensus-analysis",
      "correlation-analysis",
      "demographic-insights",
      "dimensionality-insights",
      "ensemble-analysis",
      "feature-importance-ranking",
      "feature-interactions",
      "model-performance",
      "model-selection",
      "outlier-detection",
      "predictive-modeling",
      "scenario-analysis",
      "segment-profiling",
      "sensitivity-analysis",
      "spatial-clusters",
      "strategic-analysis",
      "trend-analysis"
    ],
    "MP10138A_B": [
      "algorithm-comparison",
      "analyze",
      "anomaly-detection",
      "anomaly-insights",
      "brand-difference",
      "comparative-analysis",
      "competitive-analysis",
      "consensus-analysis",
      "correlation-analysis",
      "demographic-insights",
      "dimensionality-insights",
      "ensemble-analysis",
      "feature-importance-ranking",
      "feature-interactions",
      "model-performance",
      "model-selection",
      "outlier-detection",
      "predictive-modeling",
      "scenario-analysis",
      "segment-profiling",
      "sensitivity-analysis",
      "spatial-clusters",
      "strategic-analysis",
      "trend-analysis"
    ],
    "MP10138A_B_P": [
      "algorithm-comparison",
      "analyze",
      "anomaly-detection",
      "anomaly-insights",
      "brand-difference",
      "comparative-analysis",
      "competitive-analysis",
      "consensus-analysis",
      "correlation-analysis",
      "demographic-insights",
      "dimensionality-insights",
      "ensemble-analysis",
      "feature-importance-ranking",
      "feature-interactions",
      "model-performance",
      "model-selection",
      "outlier-detection",
      "predictive-modeling",
      "scenario-analysis",
      "segment-profiling",
      "sensitivity-analysis",
      "spatial-clusters",
      "strategic-analysis",
      "trend-analysis"
    ],
    "MP10020A_B": [
      "algorithm-comparison",
      "analyze",
      "anomaly-detection",
      "anomaly-insights",
      "brand-difference",
      "comparative-analysis",
      "competitive-analysis",
      "consensus-analysis",
      "correlation-analysis",
      "demographic-insights",
      "dimensionality-insights",
      "ensemble-analysis",
      "feature-importance-ranking",
      "feature-interactions",
      "model-performance",
      "model-selection",
      "outlier-detection",
      "predictive-modeling",
      "scenario-analysis",
      "segment-profiling",
      "sensitivity-analysis",
      "spatial-clusters",
      "strategic-analysis",
      "trend-analysis"
    ],
    "MP10020A_B_P": [
      "algorithm-comparison",
      "analyze",
      "anomaly-detection",
      "anomaly-insights",
      "brand-difference",
      "comparative-analysis",
      "competitive-analysis",
      "consensus-analysis",
      "correlation-analysis",
      "demographic-insights",
      "dimensionality-insights",
      "ensemble-analysis",
      "feature-importance-ranking",
      "feature-interactions",
      "model-performance",
      "model-selection",
      "outlier-detection",
      "predictive-modeling",
      "scenario-analysis",
      "segment-profiling",
      "sensitivity-analysis",
      "spatial-clusters",
      "strategic-analysis",
      "trend-analysis"
    ],
    "X14058_X": [
      "algorithm-comparison",
      "analyze",
      "anomaly-detection",
      "anomaly-insights",
      "brand-difference",
      "comparative-analysis",
      "competitive-analysis",
      "consensus-analysis",
      "correlation-analysis",
      "demographic-insights",
      "dimensionality-insights",
      "ensemble-analysis",
      "feature-importance-ranking",
      "feature-interactions",
      "model-performance",
      "model-selection",
      "outlier-detection",
      "predictive-modeling",
      "scenario-analysis",
      "segment-profiling",
      "sensitivity-analysis",
      "spatial-clusters",
      "strategic-analysis",
      "trend-analysis"
    ],
    "X14058_X_A": [
      "algorithm-comparison",
      "analyze",
      "anomaly-detection",
      "anomaly-insights",
      "brand-difference",
      "comparative-analysis",
      "competitive-analysis",
      "consensus-analysis",
      "correlation-analysis",
      "demographic-insights",
      "dimensionality-insights",
      "ensemble-analysis",
      "feature-importance-ranking",
      "feature-interactions",
      "model-performance",
      "model-selection",
      "outlier-detection",
      "predictive-modeling",
      "scenario-analysis",
      "segment-profiling",
      "sensitivity-analysis",
      "spatial-clusters",
      "strategic-analysis",
      "trend-analysis"
    ],
    "GENZ_CY": [
      "algorithm-comparison",
      "analyze",
      "anomaly-detection",
      "anomaly-insights",
      "brand-difference",
      "comparative-analysis",
      "competitive-analysis",
      "consensus-analysis",
      "correlation-analysis",
      "demographic-insights",
      "dimensionality-insights",
      "ensemble-analysis",
      "feature-importance-ranking",
      "feature-interactions",
      "model-performance",
      "model-selection",
      "outlier-detection",
      "predictive-modeling",
      "scenario-analysis",
      "segment-profiling",
      "sensitivity-analysis",
      "spatial-clusters",
      "strategic-analysis",
      "trend-analysis"
    ],
    "GENZ_CY_P": [
      "algorithm-comparison",
      "analyze",
      "anomaly-detection",
      "anomaly-insights",
      "brand-difference",
      "comparative-analysis",
      "competitive-analysis",
      "consensus-analysis",
      "correlation-analysis",
      "demographic-insights",
      "dimensionality-insights",
      "ensemble-analysis",
      "feature-importance-ranking",
      "feature-interactions",
      "model-performance",
      "model-selection",
      "outlier-detection",
      "predictive-modeling",
      "scenario-analysis",
      "segment-profiling",
      "sensitivity-analysis",
      "spatial-clusters",
      "strategic-analysis",
      "trend-analysis"
    ],
    "MP10028A_B": [
      "algorithm-comparison",
      "analyze",
      "anomaly-detection",
      "anomaly-insights",
      "brand-difference",
      "comparative-analysis",
      "competitive-analysis",
      "consensus-analysis",
      "correlation-analysis",
      "demographic-insights",
      "dimensionality-insights",
      "ensemble-analysis",
      "feature-importance-ranking",
      "feature-interactions",
      "model-performance",
      "model-selection",
      "outlier-detection",
      "predictive-modeling",
      "scenario-analysis",
      "segment-profiling",
      "sensitivity-analysis",
      "spatial-clusters",
      "strategic-analysis",
      "trend-analysis"
    ],
    "MP10028A_B_P": [
      "algorithm-comparison",
      "analyze",
      "anomaly-detection",
      "anomaly-insights",
      "brand-difference",
      "comparative-analysis",
      "competitive-analysis",
      "consensus-analysis",
      "correlation-analysis",
      "demographic-insights",
      "dimensionality-insights",
      "ensemble-analysis",
      "feature-importance-ranking",
      "feature-interactions",
      "model-performance",
      "model-selection",
      "outlier-detection",
      "predictive-modeling",
      "scenario-analysis",
      "segment-profiling",
      "sensitivity-analysis",
      "spatial-clusters",
      "strategic-analysis",
      "trend-analysis"
    ],
    "MP10110A_B": [
      "algorithm-comparison",
      "analyze",
      "anomaly-detection",
      "anomaly-insights",
      "brand-difference",
      "comparative-analysis",
      "competitive-analysis",
      "consensus-analysis",
      "correlation-analysis",
      "demographic-insights",
      "dimensionality-insights",
      "ensemble-analysis",
      "feature-importance-ranking",
      "feature-interactions",
      "model-performance",
      "model-selection",
      "outlier-detection",
      "predictive-modeling",
      "scenario-analysis",
      "segment-profiling",
      "sensitivity-analysis",
      "spatial-clusters",
      "strategic-analysis",
      "trend-analysis"
    ],
    "MP10110A_B_P": [
      "algorithm-comparison",
      "analyze",
      "anomaly-detection",
      "anomaly-insights",
      "brand-difference",
      "comparative-analysis",
      "competitive-analysis",
      "consensus-analysis",
      "correlation-analysis",
      "demographic-insights",
      "dimensionality-insights",
      "ensemble-analysis",
      "feature-importance-ranking",
      "feature-interactions",
      "model-performance",
      "model-selection",
      "outlier-detection",
      "predictive-modeling",
      "scenario-analysis",
      "segment-profiling",
      "sensitivity-analysis",
      "spatial-clusters",
      "strategic-analysis",
      "trend-analysis"
    ],
    "MP10120A_B": [
      "algorithm-comparison",
      "analyze",
      "anomaly-detection",
      "anomaly-insights",
      "brand-difference",
      "comparative-analysis",
      "competitive-analysis",
      "consensus-analysis",
      "correlation-analysis",
      "demographic-insights",
      "dimensionality-insights",
      "ensemble-analysis",
      "feature-importance-ranking",
      "feature-interactions",
      "model-performance",
      "model-selection",
      "outlier-detection",
      "predictive-modeling",
      "scenario-analysis",
      "segment-profiling",
      "sensitivity-analysis",
      "spatial-clusters",
      "strategic-analysis",
      "trend-analysis"
    ],
    "MP10120A_B_P": [
      "algorithm-comparison",
      "analyze",
      "anomaly-detection",
      "anomaly-insights",
      "brand-difference",
      "comparative-analysis",
      "competitive-analysis",
      "consensus-analysis",
      "correlation-analysis",
      "demographic-insights",
      "dimensionality-insights",
      "ensemble-analysis",
      "feature-importance-ranking",
      "feature-interactions",
      "model-performance",
      "model-selection",
      "outlier-detection",
      "predictive-modeling",
      "scenario-analysis",
      "segment-profiling",
      "sensitivity-analysis",
      "spatial-clusters",
      "strategic-analysis",
      "trend-analysis"
    ],
    "GENALPHACY": [
      "algorithm-comparison",
      "analyze",
      "anomaly-detection",
      "anomaly-insights",
      "brand-difference",
      "comparative-analysis",
      "competitive-analysis",
      "consensus-analysis",
      "correlation-analysis",
      "demographic-insights",
      "dimensionality-insights",
      "ensemble-analysis",
      "feature-importance-ranking",
      "feature-interactions",
      "model-performance",
      "model-selection",
      "outlier-detection",
      "predictive-modeling",
      "scenario-analysis",
      "segment-profiling",
      "sensitivity-analysis",
      "spatial-clusters",
      "strategic-analysis",
      "trend-analysis"
    ],
    "GENALPHACY_P": [
      "algorithm-comparison",
      "analyze",
      "anomaly-detection",
      "anomaly-insights",
      "brand-difference",
      "comparative-analysis",
      "competitive-analysis",
      "consensus-analysis",
      "correlation-analysis",
      "demographic-insights",
      "dimensionality-insights",
      "ensemble-analysis",
      "feature-importance-ranking",
      "feature-interactions",
      "model-performance",
      "model-selection",
      "outlier-detection",
      "predictive-modeling",
      "scenario-analysis",
      "segment-profiling",
      "sensitivity-analysis",
      "spatial-clusters",
      "strategic-analysis",
      "trend-analysis"
    ],
    "algorithm_performance_score": [
      "algorithm-comparison"
    ],
    "algorithm_predictions": [
      "algorithm-comparison"
    ],
    "best_algorithm": [
      "algorithm-comparison"
    ],
    "consensus_prediction": [
      "algorithm-comparison"
    ],
    "algorithm_agreement": [
      "algorithm-comparison"
    ],
    "algorithm_agreement_score": [
      "algorithm-comparison"
    ],
    "algorithm_reliability_score": [
      "algorithm-comparison"
    ],
    "prediction_consensus_score": [
      "algorithm-comparison"
    ],
    "best_algorithm_confidence_score": [
      "algorithm-comparison"
    ],
    "model_diversity_benefit_score": [
      "algorithm-comparison"
    ],
    "algorithm_comparison_score": [
      "algorithm-comparison",
      "correlation-analysis"
    ],
    "analysis_score": [
      "analyze"
    ],
    "opportunity_score": [
      "analyze"
    ],
    "value": [
      "analyze"
    ],
    "analyze_score": [
      "analyze",
      "correlation-analysis"
    ],
    "anomaly_score": [
      "anomaly-detection",
      "anomaly-insights"
    ],
    "anomaly_detection_score": [
      "anomaly-detection",
      "correlation-analysis"
    ],
    "anomaly_performance_score": [
      "anomaly-insights"
    ],
    "is_anomaly": [
      "anomaly-insights"
    ],
    "anomaly_type": [
      "anomaly-insights"
    ],
    "opportunity_rating": [
      "anomaly-insights"
    ],
    "anomaly_explanation": [
      "anomaly-insights"
    ],
    "anomaly_insight_score": [
      "anomaly-insights"
    ],
    "anomaly_significance_score": [
      "anomaly-insights"
    ],
    "opportunity_detection_score": [
      "anomaly-insights"
    ],
    "outlier_strength_score": [
      "anomaly-insights"
    ],
    "market_anomaly_value_score": [
      "anomaly-insights"
    ],
    "investigation_priority_score": [
      "anomaly-insights"
    ],
    "anomaly_reliability_score": [
      "anomaly-insights"
    ],
    "high_opportunity_anomaly": [
      "anomaly-insights"
    ],
    "strong_outlier": [
      "anomaly-insights"
    ],
    "investigation_recommended": [
      "anomaly-insights"
    ],
    "positive_market_signal": [
      "anomaly-insights"
    ],
    "anomaly_category": [
      "anomaly-insights"
    ],
    "anomaly_insights_score": [
      "anomaly-insights",
      "correlation-analysis"
    ],
    "brand_difference_score": [
      "brand-difference",
      "correlation-analysis"
    ],
    "comparison_score": [
      "comparative-analysis"
    ],
    "comparative_score": [
      "comparative-analysis"
    ],
    "comparative_analysis_score": [
      "comparative-analysis",
      "correlation-analysis"
    ],
    "competitive_score": [
      "competitive-analysis"
    ],
    "competitive_advantage_score": [
      "competitive-analysis"
    ],
    "market_dominance": [
      "competitive-analysis"
    ],
    "demographic_advantage": [
      "competitive-analysis"
    ],
    "economic_advantage": [
      "competitive-analysis"
    ],
    "population_advantage": [
      "competitive-analysis"
    ],
    "competitive_components": [
      "competitive-analysis"
    ],
    "competitive_analysis_score": [
      "competitive-analysis",
      "correlation-analysis"
    ],
    "consensus_performance_score": [
      "consensus-analysis"
    ],
    "model_predictions": [
      "consensus-analysis"
    ],
    "voting_results": [
      "consensus-analysis"
    ],
    "uncertainty_measures": [
      "consensus-analysis"
    ],
    "consensus_quality": [
      "consensus-analysis"
    ],
    "consensus_score": [
      "consensus-analysis"
    ],
    "model_agreement_score": [
      "consensus-analysis"
    ],
    "consensus_confidence_score": [
      "consensus-analysis"
    ],
    "prediction_reliability_score": [
      "consensus-analysis"
    ],
    "uncertainty_quantification_score": [
      "consensus-analysis"
    ],
    "voting_consensus_strength_score": [
      "consensus-analysis"
    ],
    "multi_model_value_score": [
      "consensus-analysis"
    ],
    "high_model_agreement": [
      "consensus-analysis"
    ],
    "reliable_consensus": [
      "consensus-analysis"
    ],
    "low_uncertainty": [
      "consensus-analysis"
    ],
    "strong_voting_consensus": [
      "consensus-analysis"
    ],
    "ensemble_included": [
      "consensus-analysis"
    ],
    "recommendation_confidence": [
      "consensus-analysis"
    ],
    "model_contributions": [
      "consensus-analysis"
    ],
    "consensus_analysis_score": [
      "consensus-analysis",
      "correlation-analysis"
    ],
    "correlation_score": [
      "correlation-analysis"
    ],
    "correlation_strength_score": [
      "correlation-analysis"
    ],
    "strategic_score": [
      "correlation-analysis",
      "strategic-analysis"
    ],
    "strategic_analysis_score": [
      "correlation-analysis",
      "strategic-analysis"
    ],
    "demographic_insights_score": [
      "correlation-analysis",
      "demographic-insights"
    ],
    "cluster_analysis_score": [
      "correlation-analysis"
    ],
    "correlation_analysis_score": [
      "correlation-analysis"
    ],
    "customer_profile_score": [
      "correlation-analysis"
    ],
    "dimensionality_insights_score": [
      "correlation-analysis",
      "dimensionality-insights"
    ],
    "ensemble_analysis_score": [
      "correlation-analysis",
      "ensemble-analysis"
    ],
    "feature_importance_ranking_score": [
      "correlation-analysis",
      "feature-importance-ranking"
    ],
    "feature_interactions_score": [
      "correlation-analysis",
      "feature-interactions"
    ],
    "model_performance_score": [
      "correlation-analysis",
      "model-performance"
    ],
    "model_selection_score": [
      "correlation-analysis",
      "model-selection"
    ],
    "outlier_detection_score": [
      "correlation-analysis",
      "outlier-detection"
    ],
    "predictive_modeling_score": [
      "correlation-analysis",
      "predictive-modeling"
    ],
    "scenario_analysis_score": [
      "correlation-analysis",
      "scenario-analysis"
    ],
    "segment_profiling_score": [
      "correlation-analysis",
      "segment-profiling"
    ],
    "sensitivity_analysis_score": [
      "correlation-analysis",
      "sensitivity-analysis"
    ],
    "spatial_clusters_score": [
      "correlation-analysis",
      "spatial-clusters"
    ],
    "trend_analysis_score": [
      "correlation-analysis",
      "trend-analysis"
    ],
    "demographic_score": [
      "demographic-insights"
    ],
    "demographic_opportunity_score": [
      "demographic-insights"
    ],
    "dimensionality_performance_score": [
      "dimensionality-insights"
    ],
    "component_weights": [
      "dimensionality-insights"
    ],
    "feature_loadings": [
      "dimensionality-insights"
    ],
    "variance_explained": [
      "dimensionality-insights"
    ],
    "primary_component_interpretation": [
      "dimensionality-insights"
    ],
    "dimensionality_score": [
      "dimensionality-insights"
    ],
    "feature_compression_score": [
      "dimensionality-insights"
    ],
    "component_significance_score": [
      "dimensionality-insights"
    ],
    "feature_relationship_strength_score": [
      "dimensionality-insights"
    ],
    "dimensionality_reduction_benefit_score": [
      "dimensionality-insights"
    ],
    "data_complexity_score": [
      "dimensionality-insights"
    ],
    "feature_importance_clarity_score": [
      "dimensionality-insights"
    ],
    "high_compression_efficiency": [
      "dimensionality-insights"
    ],
    "strong_feature_relationships": [
      "dimensionality-insights"
    ],
    "clear_feature_hierarchy": [
      "dimensionality-insights"
    ],
    "significant_dimensionality_reduction": [
      "dimensionality-insights"
    ],
    "data_complexity_category": [
      "dimensionality-insights"
    ],
    "ensemble_performance_score": [
      "ensemble-analysis"
    ],
    "ensemble_prediction": [
      "ensemble-analysis"
    ],
    "prediction_confidence": [
      "ensemble-analysis"
    ],
    "component_contributions": [
      "ensemble-analysis"
    ],
    "prediction_interval": [
      "ensemble-analysis"
    ],
    "ensemble_strength_score": [
      "ensemble-analysis"
    ],
    "ensemble_confidence_score": [
      "ensemble-analysis"
    ],
    "prediction_precision_score": [
      "ensemble-analysis"
    ],
    "ensemble_opportunity_score": [
      "ensemble-analysis"
    ],
    "model_component_strength_score": [
      "ensemble-analysis"
    ],
    "ensemble_reliability_score": [
      "ensemble-analysis"
    ],
    "high_performance_prediction": [
      "ensemble-analysis"
    ],
    "exceptional_confidence": [
      "ensemble-analysis"
    ],
    "importance_score": [
      "feature-importance-ranking"
    ],
    "feature_importance_score": [
      "feature-importance-ranking"
    ],
    "interaction_score": [
      "feature-interactions"
    ],
    "feature_interaction_score": [
      "feature-interactions"
    ],
    "performance_score": [
      "model-performance"
    ],
    "model_selection_performance_score": [
      "model-selection"
    ],
    "recommended_algorithm": [
      "model-selection"
    ],
    "alternative_algorithms": [
      "model-selection"
    ],
    "performance_metrics": [
      "model-selection"
    ],
    "selection_reasoning": [
      "model-selection"
    ],
    "recommendation_confidence_score": [
      "model-selection"
    ],
    "algorithm_suitability_score": [
      "model-selection"
    ],
    "model_performance_prediction_score": [
      "model-selection"
    ],
    "interpretability_benefit_score": [
      "model-selection"
    ],
    "alternative_algorithm_score": [
      "model-selection"
    ],
    "selection_reliability_score": [
      "model-selection"
    ],
    "high_confidence_recommendation": [
      "model-selection"
    ],
    "optimal_algorithm_match": [
      "model-selection"
    ],
    "interpretable_choice": [
      "model-selection"
    ],
    "high_performance_expected": [
      "model-selection"
    ],
    "algorithm_category": [
      "model-selection"
    ],
    "outlier_score": [
      "outlier-detection"
    ],
    "predictive_score": [
      "predictive-modeling"
    ],
    "scenario_score": [
      "scenario-analysis"
    ],
    "segment_score": [
      "segment-profiling"
    ],
    "sensitivity_score": [
      "sensitivity-analysis"
    ],
    "cluster_score": [
      "spatial-clusters"
    ],
    "cluster_id": [
      "spatial-clusters"
    ],
    "cluster_performance_score": [
      "spatial-clusters"
    ],
    "cluster_label": [
      "spatial-clusters"
    ],
    "strategic_value_score": [
      "strategic-analysis"
    ],
    "market_opportunity": [
      "strategic-analysis"
    ],
    "competitive_position": [
      "strategic-analysis"
    ],
    "data_reliability": [
      "strategic-analysis"
    ],
    "market_scale": [
      "strategic-analysis"
    ],
    "trend_score": [
      "trend-analysis"
    ],
    "trend_strength_score": [
      "trend-analysis"
    ]
  }
}