{
  "deployment_version": "2.0-comprehensive",
  "deployment_timestamp": "2025-08-10T20:44:15.616991",
  "endpoints": {
    "standard": [
      {
        "name": "strategic-analysis",
        "records": 984,
        "scoring_script": "strategic-analysis-scores.js"
      },
      {
        "name": "competitive-analysis",
        "records": 984,
        "scoring_script": "competitive-analysis-scores.js"
      },
      {
        "name": "demographic-insights",
        "records": 984,
        "scoring_script": "demographic-insights-scores.js"
      },
      {
        "name": "correlation-analysis",
        "records": 984,
        "scoring_script": "correlation-analysis-scores.js"
      },
      {
        "name": "predictive-modeling",
        "records": 984,
        "scoring_script": "predictive-modeling-scores.js"
      },
      {
        "name": "trend-analysis",
        "records": 984,
        "scoring_script": "trend-analysis-scores.js"
      },
      {
        "name": "spatial-clusters",
        "records": 984,
        "scoring_script": "spatial-clusters-scores.js"
      },
      {
        "name": "anomaly-detection",
        "records": 984,
        "scoring_script": "anomaly-detection-scores.js"
      },
      {
        "name": "scenario-analysis",
        "records": 984,
        "scoring_script": "scenario-analysis-scores.js"
      },
      {
        "name": "segment-profiling",
        "records": 984,
        "scoring_script": "segment-profiling-scores.js"
      },
      {
        "name": "sensitivity-analysis",
        "records": 984,
        "scoring_script": "sensitivity-analysis-scores.js"
      },
      {
        "name": "feature-interactions",
        "records": 984,
        "scoring_script": "feature-interactions-scores.js"
      },
      {
        "name": "feature-importance-ranking",
        "records": 984,
        "scoring_script": "feature-importance-ranking-scores.js"
      },
      {
        "name": "model-performance",
        "records": 984,
        "scoring_script": "model-performance-scores.js"
      },
      {
        "name": "outlier-detection",
        "records": 984,
        "scoring_script": "outlier-detection-scores.js"
      },
      {
        "name": "analyze",
        "records": 984,
        "scoring_script": "analyze-scores.js"
      },
      {
        "name": "comparative-analysis",
        "records": 984,
        "scoring_script": "comparative-analysis-scores.js"
      },
      {
        "name": "brand-difference",
        "records": 984,
        "scoring_script": "brand-difference-scores.js"
      },
      {
        "name": "customer-profile",
        "records": 984,
        "scoring_script": "customer-profile-scores.js"
      }
    ],
    "comprehensive": [
      {
        "name": "algorithm-comparison",
        "records": 984,
        "scoring_script": "algorithm-comparison-scores.js"
      },
      {
        "name": "ensemble-analysis",
        "records": 984,
        "scoring_script": "ensemble-analysis-scores.js"
      },
      {
        "name": "model-selection",
        "records": 984,
        "scoring_script": "model-selection-scores.js"
      },
      {
        "name": "anomaly-insights",
        "records": 984,
        "scoring_script": "anomaly-insights-scores.js"
      },
      {
        "name": "dimensionality-insights",
        "records": 984,
        "scoring_script": "dimensionality-insights-scores.js"
      },
      {
        "name": "consensus-analysis",
        "records": 984,
        "scoring_script": "consensus-analysis-scores.js"
      },
      {
        "name": "nonlinear-analysis",
        "records": 984,
        "scoring_script": "nonlinear-analysis-scores.js"
      },
      {
        "name": "similarity-analysis",
        "records": 984,
        "scoring_script": "similarity-analysis-scores.js"
      },
      {
        "name": "feature-selection-analysis",
        "records": 984,
        "scoring_script": "feature-selection-analysis-scores.js"
      },
      {
        "name": "interpretability-analysis",
        "records": 984,
        "scoring_script": "interpretability-analysis-scores.js"
      },
      {
        "name": "neural-network-analysis",
        "records": 984,
        "scoring_script": "neural-network-analysis-scores.js"
      },
      {
        "name": "speed-optimized-analysis",
        "records": 984,
        "scoring_script": "speed-optimized-analysis-scores.js"
      }
    ]
  },
  "model_architecture": "17-model-comprehensive",
  "total_endpoints": 32,
  "scoring_scripts": [
    "strategic-analysis-scores.js",
    "competitive-analysis-scores.js",
    "demographic-insights-scores.js",
    "correlation-analysis-scores.js",
    "predictive-modeling-scores.js",
    "trend-analysis-scores.js",
    "spatial-clusters-scores.js",
    "anomaly-detection-scores.js",
    "scenario-analysis-scores.js",
    "segment-profiling-scores.js",
    "sensitivity-analysis-scores.js",
    "feature-interactions-scores.js",
    "feature-importance-ranking-scores.js",
    "model-performance-scores.js",
    "outlier-detection-scores.js",
    "analyze-scores.js",
    "comparative-analysis-scores.js",
    "brand-difference-scores.js",
    "customer-profile-scores.js",
    "algorithm-comparison-scores.js",
    "ensemble-analysis-scores.js",
    "model-selection-scores.js",
    "anomaly-insights-scores.js",
    "dimensionality-insights-scores.js",
    "consensus-analysis-scores.js",
    "nonlinear-analysis-scores.js",
    "similarity-analysis-scores.js",
    "feature-selection-analysis-scores.js",
    "interpretability-analysis-scores.js",
    "neural-network-analysis-scores.js",
    "speed-optimized-analysis-scores.js"
  ]
}